iter8/__init__.py
iter8/discrete.py
iter8/generic.py
iter8/sliding.py
iter8-0.0.3.dist-info/DESCRIPTION.rst
iter8-0.0.3.dist-info/METADATA
iter8-0.0.3.dist-info/RECORD
iter8-0.0.3.dist-info/WHEEL
iter8-0.0.3.dist-info/metadata.json
iter8-0.0.3.dist-info/top_level.txt
