Metadata-Version: 2.0
Name: iter8
Version: 0.0.3
Summary: More itertools
Home-page: https://github.com/chbrown/iter8
Author: Christopher Brown
Author-email: io@henrian.com
License: MIT
Platform: UNKNOWN
Classifier: Development Status :: 3 - Alpha
Classifier: License :: OSI Approved :: MIT License
Classifier: Programming Language :: Python
Classifier: Programming Language :: Python :: 2.7
Classifier: Topic :: Text Processing :: General
